{"file":"_slug_-Doml_rMj.js","mappings":";;;;;;;;;;;;;;;;;;;;;;AA6UA,UAAM,QAAQ,SAAQ;AACA,qBAAgB;AACtC,UAAM,YAAY,aAAY;AAG9B,UAAM,UAAU,IAAI,IAAI;AACxB,UAAM,UAAU,IAAI,IAAI;AACxB,UAAM,kBAAkB,IAAI,CAAE,CAAA;AAC9B,UAAM,gBAAgB,IAAI,EAAE;AACC,QAAI,CAAC;AAClC,UAAM,WAAW,IAAI,CAAC;AACtB,UAAM,YAAY,IAAI,CAAC;AAGvB,UAAM,OAAO;AAAA,MACX,EAAE,IAAI,eAAe,MAAM,cAAe;AAAA,MAC1C,EAAE,IAAI,eAAe,MAAM,cAAe;AAAA,MAC1C,EAAE,IAAI,cAAc,MAAM,aAAc;AAAA,MACxC,EAAE,IAAI,WAAW,MAAM,UAAS;AAAA,IAClC;AAGA,UAAM,cAAc,YAAY;AAC9B,UAAI;AACF,gBAAQ,QAAQ;AAChB,cAAM,OAAO,MAAM,OAAO;AAG1B,cAAM,WAAW,MAAM,OAAO,iBAAiB,IAAI,EAAE;AAErD,YAAI,YAAY,SAAS,SAAS;AAChC,kBAAQ,QAAQ,SAAS;AAGzB,cAAI,QAAQ,MAAM,UAAU,QAAQ,MAAM,OAAO,SAAS,GAAG;AAC3D,0BAAc,QAAQ,QAAQ,MAAM,OAAO,CAAC;AAAA,UACpD,OAAa;AACL,0BAAc,QAAQ,QAAQ,MAAM;AAAA,UAC5C;AAGM,cAAI,SAAS,QAAQ,iBAAiB;AACpC,4BAAgB,QAAQ,SAAS,QAAQ;AAAA,UACjD;AAAA,QACA;AAAA,MACG,SAAQ,OAAO;AACd,gBAAQ,MAAM,0BAA0B,KAAK;AAC7C,gBAAQ,QAAQ;AAAA,MACpB,UAAY;AACR,gBAAQ,QAAQ;AAAA,MACpB;AAAA,IACA;AAwCA,UAAM,mBAAmB,CAAC,mBAAmB;AAC3C,YAAM,WAAW;AAAA,QACf,IAAI,eAAe;AAAA,QACnB,MAAM,eAAe;AAAA,QACrB,OAAO,eAAe;AAAA,QACtB,OAAO,eAAe,UAAU,eAAe,OAAO,SAAS,IAAI,eAAe,OAAO,CAAC,IAAI;AAAA,QAC9F,UAAU;AAAA,MACd;AAEE,gBAAU,QAAQ,QAAQ;AAC1B,YAAM,GAAG,eAAe,IAAI,iBAAiB;AAAA,IAC/C;AAOA,UAAM,MAAM,MAAM,OAAO,MAAM,MAAM;AACnC,kBAAW;AAAA,IACb,CAAC;AAGD,eAAW;AAAA,MACT,OAAO,SAAS,MAAM;;AAAA,8BAAQ,UAAR,mBAAe,SAAQ;AAAA,OAAS;AAAA,MACtD,aAAa,SAAS,MAAM;;AAAA,8BAAQ,UAAR,mBAAe,gBAAe;AAAA,OAAiB;AAAA,MAC3E,SAAS,SAAS,MAAM;;AAAA,8BAAQ,UAAR,mBAAe,SAAQ;AAAA,OAAS;AAAA,MACxD,eAAe,SAAS,MAAM;;AAAA,8BAAQ,UAAR,mBAAe,gBAAe;AAAA,OAAiB;AAAA,MAC7E,SAAS,SAAS,MAAM;;AAAA,8BAAQ,UAAR,mBAAe,WAAU,QAAQ,MAAM,OAAO,SAAS,IAAI,QAAQ,MAAM,OAAO,CAAC,IAAI;AAAA,OAA0B;AAAA,IACzI,CAAC;;;;;;;;;;;;;;;;;;;;;;;;;;;;;;;;;;;;;;;;;;;;;;;;;;;;;;;;;;;;;;;;;;;;;;;;;;;;;;;;;;;;;;;;;;;;;;;;;;;;;;;;;;;;;;;;;;;;;;;;;;;;;;;;;;;;;;;;;;;;;;;;;;;;;;;;;;;;;;;;;;;;;;;;;;;;;;;;;;;;;;;;;;;;;;;;;;;;;;;;","names":[],"sources":["../../../../pages/product/[slug].vue"],"sourcesContent":["<template>\n  <div v-if=\"loading\" class=\"flex justify-center items-center min-h-screen\">\n    <div class=\"animate-spin rounded-full h-12 w-12 border-b-2 border-blue-600\"></div>\n  </div>\n\n  <div v-else-if=\"product\" class=\"py-8 md:py-12\">\n    <div class=\"container mx-auto px-4\">\n      <!-- Breadcrumb -->\n      <nav class=\"flex mb-8\" aria-label=\"Breadcrumb\">\n        <ol class=\"inline-flex items-center space-x-1 md:space-x-3\">\n          <li class=\"inline-flex items-center\">\n            <NuxtLink to=\"/\" class=\"text-gray-500 hover:text-gray-700\">Home</NuxtLink>\n          </li>\n          <li>\n            <div class=\"flex items-center\">\n              <svg class=\"w-6 h-6 text-gray-400\" fill=\"currentColor\" viewBox=\"0 0 20 20\">\n                <path fill-rule=\"evenodd\" d=\"M7.293 14.707a1 1 0 010-1.414L10.586 10 7.293 6.707a1 1 0 011.414-1.414l4 4a1 1 0 010 1.414l-4 4a1 1 0 01-1.414 0z\" clip-rule=\"evenodd\"></path>\n              </svg>\n              <NuxtLink to=\"/products\" class=\"ml-1 text-gray-500 hover:text-gray-700 md:ml-2\">Products</NuxtLink>\n            </div>\n          </li>\n          <li v-if=\"product.category\">\n            <div class=\"flex items-center\">\n              <svg class=\"w-6 h-6 text-gray-400\" fill=\"currentColor\" viewBox=\"0 0 20 20\">\n                <path fill-rule=\"evenodd\" d=\"M7.293 14.707a1 1 0 010-1.414L10.586 10 7.293 6.707a1 1 0 011.414-1.414l4 4a1 1 0 010 1.414l-4 4a1 1 0 01-1.414 0z\" clip-rule=\"evenodd\"></path>\n              </svg>\n              <NuxtLink :to=\"`/category/${product.category.slug}`\" class=\"ml-1 text-gray-500 hover:text-gray-700 md:ml-2\">\n                {{ product.category.name }}\n              </NuxtLink>\n            </div>\n          </li>\n          <li>\n            <div class=\"flex items-center\">\n              <svg class=\"w-6 h-6 text-gray-400\" fill=\"currentColor\" viewBox=\"0 0 20 20\">\n                <path fill-rule=\"evenodd\" d=\"M7.293 14.707a1 1 0 010-1.414L10.586 10 7.293 6.707a1 1 0 011.414-1.414l4 4a1 1 0 010 1.414l-4 4a1 1 0 01-1.414 0z\" clip-rule=\"evenodd\"></path>\n              </svg>\n              <span class=\"ml-1 text-gray-500 md:ml-2\">{{ product.name }}</span>\n            </div>\n          </li>\n        </ol>\n      </nav>\n\n      <div class=\"grid grid-cols-1 lg:grid-cols-2 gap-8 lg:gap-12\">\n        <!-- Product Images -->\n        <div class=\"space-y-4\">\n          <!-- Main Image -->\n          <div class=\"aspect-square bg-gray-100 rounded-lg overflow-hidden\">\n            <img\n              :src=\"selectedImage || (product.images && product.images.length > 0 ? product.images[0] : '/placeholder-product.jpg')\"\n              :alt=\"product.name\"\n              class=\"w-full h-full object-cover\"\n            />\n          </div>\n\n          <!-- Image Thumbnails -->\n          <div v-if=\"product.images && product.images.length > 1\" class=\"flex space-x-2 overflow-x-auto\">\n            <button\n              v-for=\"(image, index) in product.images\"\n              :key=\"index\"\n              @click=\"selectedImage = image\"\n              :class=\"{ 'ring-2 ring-blue-500': selectedImage === image }\"\n              class=\"flex-shrink-0 w-20 h-20 bg-gray-100 rounded-lg overflow-hidden hover:ring-2 hover:ring-gray-300\"\n            >\n              <img :src=\"image\" :alt=\"`${product.name} ${index + 1}`\" class=\"w-full h-full object-cover\" />\n            </button>\n          </div>\n        </div>\n\n        <!-- Product Details -->\n        <div class=\"space-y-6\">\n          <!-- Product Name and Brand -->\n          <div>\n            <h1 class=\"text-3xl font-bold text-gray-900\">{{ product.name }}</h1>\n            <p v-if=\"product.brand\" class=\"text-lg text-gray-600 mt-2\">{{ product.brand }}</p>\n          </div>\n\n          <!-- Rating and Reviews -->\n          <div class=\"flex items-center space-x-4\">\n            <div class=\"flex items-center\">\n              <div class=\"flex items-center\">\n                <svg\n                  v-for=\"i in 5\"\n                  :key=\"i\"\n                  :class=\"i <= product.rating ? 'text-yellow-400' : 'text-gray-300'\"\n                  class=\"w-5 h-5\"\n                  fill=\"currentColor\"\n                  viewBox=\"0 0 20 20\"\n                >\n                  <path d=\"M9.049 2.927c.3-.921 1.603-.921 1.902 0l1.07 3.292a1 1 0 00.95.69h3.462c.969 0 1.371 1.24.588 1.81l-2.8 2.034a1 1 0 00-.364 1.118l1.07 3.292c.3.921-.755 1.688-1.54 1.118l-2.8-2.034a1 1 0 00-1.175 0l-2.8 2.034c-.784.57-1.838-.197-1.539-1.118l1.07-3.292a1 1 0 00-.364-1.118L2.98 8.72c-.783-.57-.38-1.81.588-1.81h3.461a1 1 0 00.951-.69l1.07-3.292z\" />\n                </svg>\n              </div>\n              <span class=\"ml-2 text-sm text-gray-600\">{{ product.rating }} ({{ product.reviews }} reviews)</span>\n            </div>\n          </div>\n\n          <!-- Price -->\n          <div class=\"space-y-2\">\n            <div v-if=\"product.discount > 0\" class=\"flex items-baseline space-x-3\">\n              <span class=\"text-3xl font-bold text-green-600\">${{ product.price.toFixed(2) }}</span>\n              <span class=\"text-xl text-gray-500 line-through\">${{ (product.price * (1 + product.discount / 100)).toFixed(2) }}</span>\n              <span class=\"px-3 py-1 bg-red-100 text-red-800 text-sm font-medium rounded-full\">\n                {{ product.discount }}% OFF\n              </span>\n            </div>\n            <div v-else class=\"text-3xl font-bold text-gray-900\">\n              ${{ product.price.toFixed(2) }}\n            </div>\n          </div>\n\n          <!-- Stock Status -->\n          <div class=\"flex items-center space-x-4\">\n            <div v-if=\"product.stock > 0\" class=\"flex items-center text-green-600\">\n              <svg class=\"w-5 h-5 mr-2\" fill=\"currentColor\" viewBox=\"0 0 20 20\">\n                <path fill-rule=\"evenodd\" d=\"M10 18a8 8 0 100-16 8 8 0 000 16zm3.707-9.293a1 1 0 00-1.414-1.414L9 10.586 7.707 9.293a1 1 0 00-1.414 1.414l2 2a1 1 0 001.414 0l4-4z\" clip-rule=\"evenodd\" />\n              </svg>\n              <span class=\"font-medium\">In Stock ({{ product.stock }} available)</span>\n            </div>\n            <div v-else class=\"flex items-center text-red-600\">\n              <svg class=\"w-5 h-5 mr-2\" fill=\"currentColor\" viewBox=\"0 0 20 20\">\n                <path fill-rule=\"evenodd\" d=\"M10 18a8 8 0 100-16 8 8 0 000 16zM8.707 7.293a1 1 0 00-1.414 1.414L8.586 10l-1.293 1.293a1 1 0 101.414 1.414L10 11.414l1.293 1.293a1 1 0 001.414-1.414L11.414 10l1.293-1.293a1 1 0 00-1.414-1.414L10 8.586 8.707 7.293z\" clip-rule=\"evenodd\" />\n              </svg>\n              <span class=\"font-medium\">Out of stock</span>\n            </div>\n          </div>\n\n          <!-- Product Alerts -->\n          <div class=\"space-y-2\">\n            <div v-if=\"product.isRx\" class=\"flex items-center p-3 bg-red-50 border border-red-200 rounded-lg\">\n              <svg class=\"w-5 h-5 text-red-600 mr-2\" fill=\"currentColor\" viewBox=\"0 0 20 20\">\n                <path fill-rule=\"evenodd\" d=\"M8.257 3.099c.765-1.36 2.722-1.36 3.486 0l5.58 9.92c.75 1.334-.213 2.98-1.742 2.98H4.42c-1.53 0-2.493-1.646-1.743-2.98l5.58-9.92zM11 13a1 1 0 11-2 0 1 1 0 012 0zm-1-8a1 1 0 00-1 1v3a1 1 0 002 0V6a1 1 0 00-1-1z\" clip-rule=\"evenodd\" />\n              </svg>\n              <span class=\"text-red-800 text-sm font-medium\">Prescription required for this medication</span>\n            </div>\n          </div>\n\n          <!-- Quantity and Add to Cart -->\n          <div v-if=\"product.stock > 0\" class=\"space-y-4\">\n            <div class=\"flex items-center space-x-4\">\n              <label class=\"text-sm font-medium text-gray-700\">Quantity:</label>\n              <div class=\"flex items-center border border-gray-300 rounded-lg\">\n                <button\n                  @click=\"decreaseQuantity\"\n                  :disabled=\"quantity <= 1\"\n                  class=\"px-3 py-2 text-gray-600 hover:text-gray-800 disabled:opacity-50\"\n                >\n                  -\n                </button>\n                <input\n                  v-model.number=\"quantity\"\n                  type=\"number\"\n                  :min=\"1\"\n                  :max=\"product.stock\"\n                  class=\"w-16 px-2 py-2 text-center border-0 focus:ring-0\"\n                />\n                <button\n                  @click=\"increaseQuantity\"\n                  :disabled=\"quantity >= product.stock\"\n                  class=\"px-3 py-2 text-gray-600 hover:text-gray-800 disabled:opacity-50\"\n                >\n                  +\n                </button>\n              </div>\n            </div>\n\n            <div class=\"flex space-x-4\">\n              <button\n                @click=\"addToCart\"\n                class=\"flex-1 bg-blue-600 text-white px-6 py-3 rounded-lg font-medium hover:bg-blue-700 focus:outline-none focus:ring-2 focus:ring-blue-500 focus:ring-offset-2\"\n              >\n                Add to Cart\n              </button>\n              <button\n                @click=\"buyNow\"\n                class=\"flex-1 bg-green-600 text-white px-6 py-3 rounded-lg font-medium hover:bg-green-700 focus:outline-none focus:ring-2 focus:ring-green-500 focus:ring-offset-2\"\n              >\n                Buy Now\n              </button>\n            </div>\n          </div>\n\n          <!-- Out of Stock Message -->\n          <div v-else class=\"space-y-4\">\n            <div class=\"text-center p-4 bg-red-50 border border-red-200 rounded-lg\">\n              <p class=\"text-red-800 font-medium\">This product is currently out of stock.</p>\n              <p class=\"text-red-600 text-sm mt-1\">Check back later or contact us for availability.</p>\n            </div>\n          </div>\n\n          <!-- Product Information Tabs -->\n          <div class=\"mt-8\">\n            <div class=\"border-b border-gray-200\">\n              <nav class=\"-mb-px flex space-x-8\">\n                <button\n                  v-for=\"(tab, index) in tabs\"\n                  :key=\"tab.id\"\n                  @click=\"activeTab = index\"\n                  :class=\"{\n                    'border-blue-500 text-blue-600': activeTab === index,\n                    'border-transparent text-gray-500 hover:text-gray-700 hover:border-gray-300': activeTab !== index\n                  }\"\n                  class=\"whitespace-nowrap py-4 px-1 border-b-2 font-medium text-sm\"\n                >\n                  {{ tab.name }}\n                </button>\n              </nav>\n            </div>\n\n            <div class=\"mt-6\">\n              <!-- Description Tab -->\n              <div v-show=\"activeTab === 0\" class=\"prose max-w-none\">\n                <p class=\"text-gray-700 mb-4\">{{ product.description }}</p>\n              </div>\n\n              <!-- Ingredients Tab -->\n              <div v-show=\"activeTab === 1\" class=\"prose max-w-none\">\n                <div v-if=\"product.ingredients\">\n                  <div v-if=\"Array.isArray(product.ingredients)\" class=\"mb-4\">\n                    <h4 class=\"font-semibold text-lg mb-2\">Active Ingredients:</h4>\n                    <ul class=\"list-disc pl-5\">\n                      <li v-for=\"(ingredient, index) in product.ingredients\" :key=\"index\" class=\"mb-1\">\n                        {{ ingredient }}\n                      </li>\n                    </ul>\n                  </div>\n                  <div v-else class=\"mb-4\">\n                    <p>{{ product.ingredients }}</p>\n                  </div>\n                </div>\n                <div v-else class=\"text-gray-500\">Information about the ingredients is currently not available for this product.</div>\n              </div>\n\n              <!-- Directions Tab -->\n              <div v-show=\"activeTab === 2\" class=\"prose max-w-none\">\n                <div v-if=\"product.directions\">\n                  <p class=\"mb-4\">{{ product.directions }}</p>\n                  \n                  <div v-if=\"product.dosage\" class=\"mb-4\">\n                    <h4 class=\"font-semibold text-lg mb-2\">Recommended Dosage:</h4>\n                    <p>{{ product.dosage }}</p>\n                  </div>\n                  \n                  <div v-if=\"product.warnings && product.warnings.length > 0\" class=\"bg-yellow-50 border border-yellow-200 rounded-md p-4 mt-4\">\n                    <h4 class=\"font-semibold text-yellow-700 mb-2\">Important Warnings:</h4>\n                    <ul class=\"list-disc pl-5 text-yellow-700\">\n                      <li v-for=\"(warning, index) in product.warnings\" :key=\"index\" class=\"mb-1\">\n                        {{ warning }}\n                      </li>\n                    </ul>\n                  </div>\n                </div>\n                <div v-else class=\"text-gray-500\">Detailed usage directions are currently not available for this product.</div>\n              </div>\n\n              <!-- Reviews Tab -->\n              <div v-show=\"activeTab === 3\">\n                <div class=\"space-y-6\">\n                  <div class=\"flex items-center justify-between\">\n                    <h3 class=\"text-lg font-medium\">Customer Reviews</h3>\n                    <button class=\"text-blue-600 hover:text-blue-700 text-sm font-medium\">Write a Review</button>\n                  </div>\n                  \n                  <div v-if=\"product.reviewList && product.reviewList.length > 0\" class=\"space-y-4\">\n                    <div v-for=\"(review, index) in product.reviewList\" :key=\"index\" class=\"border-b border-gray-200 pb-4\">\n                      <div class=\"flex items-center justify-between mb-2\">\n                        <div class=\"flex items-center space-x-2\">\n                          <div class=\"w-10 h-10 rounded-full bg-blue-100 flex items-center justify-center text-blue-700 font-medium text-lg\">\n                            {{ review.name.charAt(0) }}\n                          </div>\n                          <div>\n                            <p class=\"font-medium text-gray-800\">{{ review.name }}</p>\n                            <p class=\"text-xs text-gray-500\">{{ review.date }}</p>\n                          </div>\n                        </div>\n                        <div class=\"flex items-center\">\n                          <svg\n                            v-for=\"i in 5\"\n                            :key=\"i\"\n                            :class=\"i <= review.rating ? 'text-yellow-400' : 'text-gray-300'\"\n                            class=\"w-4 h-4\"\n                            fill=\"currentColor\"\n                            viewBox=\"0 0 20 20\"\n                          >\n                            <path d=\"M9.049 2.927c.3-.921 1.603-.921 1.902 0l1.07 3.292a1 1 0 00.95.69h3.462c.969 0 1.371 1.24.588 1.81l-2.8 2.034a1 1 0 00-.364 1.118l1.07 3.292c.3.921-.755 1.688-1.54 1.118l-2.8-2.034a1 1 0 00-1.175 0l-2.8 2.034c-.784.57-1.838-.197-1.539-1.118l1.07-3.292a1 1 0 00-.364-1.118L2.98 8.72c-.783-.57-.38-1.81.588-1.81h3.461a1 1 0 00.951-.69l1.07-3.292z\" />\n                          </svg>\n                        </div>\n                      </div>\n                      <p class=\"text-gray-700\">{{ review.comment }}</p>\n                    </div>\n                  </div>\n                  \n                  <div v-else class=\"text-center py-8\">\n                    <p class=\"text-gray-500 mb-3\">No reviews yet</p>\n                    <button class=\"text-blue-600 hover:text-blue-700 text-sm font-medium\">Be the first to write a review</button>\n                  </div>\n                </div>\n              </div>\n            </div>\n          </div>\n        </div>\n      </div>\n\n      <!-- Related Products -->\n      <div class=\"mt-16\">\n        <h2 class=\"text-2xl font-bold text-gray-900 mb-8\">Related Products</h2>\n        <div class=\"grid grid-cols-1 sm:grid-cols-2 lg:grid-cols-4 gap-6\">\n          <ProductCard\n            v-for=\"relatedProduct in relatedProducts\"\n            :key=\"relatedProduct.id\"\n            :product=\"relatedProduct\"\n            @add-to-cart=\"addRelatedToCart\"\n          />\n        </div>\n      </div>\n    </div>\n  </div>\n\n  <!-- Product Not Found -->\n  <div v-else class=\"py-16 text-center\">\n    <div class=\"max-w-md mx-auto\">\n      <h1 class=\"text-2xl font-bold text-gray-900 mb-4\">Product Not Found</h1>\n      <p class=\"text-gray-600 mb-8\">The product you're looking for doesn't exist or has been removed.</p>\n      <NuxtLink to=\"/products\" class=\"bg-blue-600 text-white px-6 py-3 rounded-lg font-medium hover:bg-blue-700\">\n        Browse Products\n      </NuxtLink>\n    </div>\n  </div>\n</template>\n\n<script setup>\nimport { useProductsStore } from '~/stores/products'\nimport { useCartStore } from '~/stores/cart'\nimport ProductCard from '~/components/ProductCard.vue' \n\nconst route = useRoute()\nconst productsStore = useProductsStore()\nconst cartStore = useCartStore()\n\n// Reactive data\nconst loading = ref(true)\nconst product = ref(null)\nconst relatedProducts = ref([])\nconst selectedImage = ref('')\nconst selectedVariantIndex = ref(0)\nconst quantity = ref(1)\nconst activeTab = ref(0) // Using index instead of ID for consistency\n\n// Tabs configuration\nconst tabs = [\n  { id: 'description', name: 'Description' },\n  { id: 'ingredients', name: 'Ingredients' },\n  { id: 'directions', name: 'Directions' },\n  { id: 'reviews', name: 'Reviews' }\n]\n\n// Load product data\nconst loadProduct = async () => {\n  try {\n    loading.value = true\n    const slug = route.params.slug\n    \n    // Fetch product by slug from API (using the correct endpoint)\n    const response = await $fetch(`/api/products/${slug}`)\n    \n    if (response && response.product) {\n      product.value = response.product\n      \n      // Set default selected image\n      if (product.value.images && product.value.images.length > 0) {\n        selectedImage.value = product.value.images[0]\n      } else {\n        selectedImage.value = product.value.image\n      }\n      \n      // Related products are included in the API response\n      if (response.product.relatedProducts) {\n        relatedProducts.value = response.product.relatedProducts\n      }\n    }\n  } catch (error) {\n    console.error('Error loading product:', error)\n    product.value = null\n  } finally {\n    loading.value = false\n  }\n}\n\n// Methods\nconst decreaseQuantity = () => {\n  if (quantity.value > 1) {\n    quantity.value--\n  }\n}\n\nconst increaseQuantity = () => {\n  const maxQty = product.value?.stock || 0\n  if (quantity.value < maxQty) {\n    quantity.value++\n  }\n}\n\nconst addToCart = () => {\n  if (!product.value) return\n  \n  const cartItem = {\n    id: product.value.id,\n    name: product.value.name,\n    price: product.value.price,\n    image: product.value.images && product.value.images.length > 0 ? product.value.images[0] : '/placeholder-product.jpg',\n    quantity: quantity.value,\n    selectedVariant: product.value.variants?.[selectedVariantIndex.value] || null\n  }\n  \n  cartStore.addItem(cartItem)\n  \n  // Show success message (you can implement a toast notification here)\n  alert(`${product.value.name} added to cart!`)\n}\n\nconst buyNow = () => {\n  addToCart()\n  // Redirect to checkout\n  navigateTo('/checkout')\n}\n\nconst addRelatedToCart = (relatedProduct) => {\n  const cartItem = {\n    id: relatedProduct.id,\n    name: relatedProduct.name,\n    price: relatedProduct.price,\n    image: relatedProduct.images && relatedProduct.images.length > 0 ? relatedProduct.images[0] : '/placeholder-product.jpg',\n    quantity: 1\n  }\n  \n  cartStore.addItem(cartItem)\n  alert(`${relatedProduct.name} added to cart!`)\n}\n\n// Load product when component mounts or route changes\nonMounted(() => {\n  loadProduct()\n})\n\nwatch(() => route.params.slug, () => {\n  loadProduct()\n})\n\n// SEO Meta tags\nuseSeoMeta({\n  title: computed(() => product.value?.name || 'Product'),\n  description: computed(() => product.value?.description || 'Product details'),\n  ogTitle: computed(() => product.value?.name || 'Product'),\n  ogDescription: computed(() => product.value?.description || 'Product details'),\n  ogImage: computed(() => product.value?.images && product.value.images.length > 0 ? product.value.images[0] : '/placeholder-product.jpg')\n})\n</script>\n\n<style scoped>\n.animate-spin {\n  animation: spin 1s linear infinite;\n}\n\n@keyframes spin {\n  from { transform: rotate(0deg); }\n  to { transform: rotate(360deg); }\n}\n\n.prose {\n  color: #374151;\n  line-height: 1.75;\n}\n\n.prose p {\n  margin-bottom: 1.25em;\n}\n\n.prose h4 {\n  font-weight: 600;\n  color: #1f2937;\n  margin-bottom: 0.5em;\n  margin-top: 1.5em;\n}\n\n.prose ul {\n  margin-bottom: 1.25em;\n}\n\n.prose li {\n  margin-bottom: 0.5em;\n}\n</style>\n"],"version":3}